Metadata-Version: 1.0
Name: sama-probability
Version: 0.1
Summary: Gaussian distributions
Home-page: UNKNOWN
Author: SilEye
Author-email: samaemail@something.com
License: UNKNOWN
Platform: UNKNOWN
